[
    {
        "type": "MC",
        "text": "Pick the best description for: Tres Castillos",
        "answers": [
            {"text": "A reservation established by the US Government in 1870"},
            {"text": "Site of the massacre between Joaquin Terrazas troops and Victorio and Apaches","correct":"true"},
            {"text": "The man responsible for cornering Cochise and his few companions at Apache Pass in southeastern Arizona."},
            {"text": "Governor of Chihuahua in 1850 and supporter of the La Ascension settlement"}
        ]
    },
    {
        "type": "MC",
        "text": "Pick the best description for: Ojo Caliente",
        "answers": [
            {"text": "A reservation established by the US Government in 1870","correct":"true"},
            {"text": "Apache war chief who was the leader of the Coppermine Mimbrenos people"},
            {"text": "An Apache chief who led many of his people in an 1879 breakout from a New Mexico reservation"},
            {"text": "Governor of Chihuahua in 1850 and supporter of the La Ascension settlement"}
        ]
    },
    {
        "type": "MC",
        "text": "Pick the best description for: San Carlos",
        "answers": [
            {"text": "The man responsible for cornering Cochise and his few companions at Apache Pass in southeastern Arizona."},
            {"text": "Site of the massacre between Joaquin Terrazas troops and Victorio and Apaches"},
            {"text": "A reservation established by the US Government in 1870"},
            {"text": "A reservation in eastern Arizona intended for all bands of the Apache people to be placed","correct":"true"}
        ]
    },
    {
        "type": "MC",
        "text": "Pick the best description for: Luis Terrazas",
        "answers": [
            {"text": "Apache war chief who was the leader of the Coppermine Mimbrenos people"},
            {"text": "An Apache chief who led many of his people in an 1879 breakout from a New Mexico reservation"},
            {"text": "Governor of Chihuahua in 1850 and supporter of the La Ascension settlement","correct":"true"},
            {"text": "The man responsible for cornering Cochise and his few companions at Apache Pass in southeastern Arizona."}
        ]
    },
    {
        "type": "MC",
        "text": "Pick the best description for: Victorio",
        "answers": [
            {"text": "An Apache chief who led many of his people in an 1879 breakout from a New Mexico reservation","correct":"true"},
            {"text": "The man responsible for cornering Cochise and his few companions at Apache Pass in southeastern Arizona."},
            {"text": "Apache war chief who was the leader of the Coppermine Mimbrenos people"},
            {"text": "Governor of Chihuahua in 1850 and supporter of the La Ascension settlement"}
        ]
    },
    {
        "type": "MC",
        "text": "Pick the best description for: Mangas",
        "answers": [
            {"text": "African American men serving in the Army after the civil war"},
            {"text": "The man responsible for cornering Cochise and his few companions at Apache Pass in southeastern Arizona."},
            {"text": "Apache war chief who was the leader of the Coppermine Mimbrenos people","correct":"true"},
            {"text": "An Apache chief who led many of his people in an 1879 breakout from a New Mexico reservation"}
        ]
    },
    {
        "type": "MC",
        "text": "Pick the best description for: Lt. George N. Bascom",
        "answers": [
            {"text": "Apache war chief who was the leader of the Coppermine Mimbrenos people"},
            {"text": "The man responsible for cornering Cochise and his few companions at Apache Pass in southeastern Arizona.","correct":"true"},
            {"text": "Governor of Chihuahua in 1850 and supporter of the La Ascension settlement"},
            {"text": "An Apache chief who led many of his people in an 1879 breakout from a New Mexico reservation"}
        ]
    },
    {
        "type": "MC",
        "text": "In 1846 when the US went to war with Mexico the Apache people gave the U.S. Military safe passage through their land because",
        "answers": [
            {"text": "they thought they were passing through to Arizona and California and would not stay on their land."},
            {"text": "they wanted to learn the white man’s language and customs in order to communicate and live among them."},
            {"text": "there were better trade items and supplies being brought from the east."},
            {"text": "they thought that the Military could aid them in their fight against the Mexicans to ensure the land would belong to the Apache people.","correct":"true"}
        ]
    },
    {
        "type": "MC",
        "text": "The Pacific Railroad Act was expressly designed to",
        "answers": [
            {"text": "establish a transcontinental rail route.","correct":"true"},
            {"text": "enable Sheldon Cooper’s fascination with trains. "},
            {"text": "create a competition between New Orleans, St. Louis and Chicago to complete a transcontinental route."},
            {"text": "ship fresher produce from California to the East."}
        ]
    },
    {
        "type": "MC",
        "text": "Promoting New Mexico as the Colorful Southwest Indian Country and the Land of Enchantment were created in an effort to",
        "answers": [
            {"text": "to show US citizens that we had civilized the Native Americans."},
            {"text": "promote Fred Harvey Hotels."},
            {"text": "create new forms of art and jewelery."},
            {"text": "resetablish the Santa Fe Railroad financially.","correct":"true"}
        ]
    }
]